odoo/addons/mis_builder_budget_product/README.rst
odoo/addons/mis_builder_budget_product/__init__.py
odoo/addons/mis_builder_budget_product/__manifest__.py
odoo/addons/mis_builder_budget_product/i18n/it.po
odoo/addons/mis_builder_budget_product/i18n/mis_builder_budget_product.pot
odoo/addons/mis_builder_budget_product/models/__init__.py
odoo/addons/mis_builder_budget_product/models/mis_budget_by_account_item.py
odoo/addons/mis_builder_budget_product/readme/CONTRIBUTORS.rst
odoo/addons/mis_builder_budget_product/readme/CREDITS.rst
odoo/addons/mis_builder_budget_product/readme/DESCRIPTION.rst
odoo/addons/mis_builder_budget_product/readme/HISTORY.rst
odoo/addons/mis_builder_budget_product/readme/ROADMAP.rst
odoo/addons/mis_builder_budget_product/readme/USAGE.rst
odoo/addons/mis_builder_budget_product/static/description/icon.png
odoo/addons/mis_builder_budget_product/static/description/index.html
odoo/addons/mis_builder_budget_product/views/mis_budget_by_account_item.xml
odoo_addon_mis_builder_budget_product-16.0.1.0.0.6.dist-info/METADATA
odoo_addon_mis_builder_budget_product-16.0.1.0.0.6.dist-info/WHEEL
odoo_addon_mis_builder_budget_product-16.0.1.0.0.6.dist-info/top_level.txt
odoo_addon_mis_builder_budget_product-16.0.1.0.0.6.dist-info/RECORD
